HowdenFileInspector/__init__.py
HowdenFileInspector/parser_view/__init__.py
HowdenFileInspector/parser_view/parser_view.py
howdenfileinspector-0.1.5.dist-info/METADATA
howdenfileinspector-0.1.5.dist-info/WHEEL
howdenfileinspector-0.1.5.dist-info/RECORD
