Metadata-Version: 2.3
Name: HowdenFileInspector
Version: 0.1.5
Summary: A simple configuration manager with Pydantic and JSON export.
License: MIT
Keywords: config,configuration,pydantic,json
Author: JesperThoftIllemannJ
Author-email: jesper.jaeger@howdendanmark.dk
Requires-Python: >=3.12
Classifier: License :: OSI Approved :: MIT License
Classifier: Programming Language :: Python :: 3
Classifier: Programming Language :: Python :: 3.12
Classifier: Programming Language :: Python :: 3.13
Requires-Dist: gradio (>=5.42.0,<6.0.0)
Requires-Dist: pymupdf (>=1.26.3,<2.0.0)
Project-URL: Documentation, https://github.com/yourusername/config
Project-URL: Homepage, https://github.com/yourusername/config
Project-URL: Repository, https://github.com/yourusername/config
